get_some_ncbi_genomes.py
get_some_ncbi_genomes-0.3.3.dist-info/licenses/LICENSE
get_some_ncbi_genomes-0.3.3.dist-info/METADATA
get_some_ncbi_genomes-0.3.3.dist-info/WHEEL
get_some_ncbi_genomes-0.3.3.dist-info/entry_points.txt
get_some_ncbi_genomes-0.3.3.dist-info/top_level.txt
get_some_ncbi_genomes-0.3.3.dist-info/RECORD
