Metadata-Version: 2.4
Name: get-some-ncbi-genomes
Version: 0.3.3
Summary: download one or more NCBI genomes by accession
Requires-Python: >=3.11
License-File: LICENSE
Requires-Dist: sourmash<5,>=4.9.0
Requires-Dist: lxml<7,>=6.0.1
Dynamic: license-file
